MANIFEST.in
README
setup.py
redsolutioncms/__init__.py
redsolutioncms/__init__.pyc
redsolutioncms/admin.py
redsolutioncms/django.po
redsolutioncms/ez_setup.py
redsolutioncms/forms.py
redsolutioncms/importpath.py
redsolutioncms/loader.py
redsolutioncms/make.py
redsolutioncms/manage.py
redsolutioncms/models.py
redsolutioncms/packages.py
redsolutioncms/settings.py
redsolutioncms/urls.py
redsolutioncms/utils.py
redsolutioncms/views.py
redsolutioncms/xmlrpc_urllib2_transport.py
redsolutioncms.egg-info/PKG-INFO
redsolutioncms.egg-info/SOURCES.txt
redsolutioncms.egg-info/dependency_links.txt
redsolutioncms.egg-info/entry_points.txt
redsolutioncms.egg-info/not-zip-safe
redsolutioncms.egg-info/top_level.txt
redsolutioncms/home/bootstrap.py
redsolutioncms/home/buildout.cfg
redsolutioncms/home/extrapath_additional.py
redsolutioncms/home/settings_additional.py
redsolutioncms/home/urls_additional.py
redsolutioncms/locale/ru/LC_MESSAGES/django.mo
redsolutioncms/locale/ru/LC_MESSAGES/django.po
redsolutioncms/management/__init__.py
redsolutioncms/management/commands/__init__.py
redsolutioncms/management/commands/change_settings.py
redsolutioncms/management/commands/install_packages.py
redsolutioncms/management/commands/kill_runserver.py
redsolutioncms/management/commands/open_browser.py
redsolutioncms/management/commands/wrap_runserver.py
redsolutioncms/media/css/admin_additional.css
redsolutioncms/media/css/admin_base.css
redsolutioncms/media/css/style.css
redsolutioncms/media/img/favicon.ico
redsolutioncms/media/img/loading.gif
redsolutioncms/media/img/nav-bg.gif
redsolutioncms/media/img/admin/arrow-down.gif
redsolutioncms/media/img/admin/arrow-up.gif
redsolutioncms/media/img/admin/changelist-bg.gif
redsolutioncms/media/img/admin/changelist-bg_rtl.gif
redsolutioncms/media/img/admin/chooser-bg.gif
redsolutioncms/media/img/admin/chooser_stacked-bg.gif
redsolutioncms/media/img/admin/default-bg-reverse.gif
redsolutioncms/media/img/admin/default-bg.gif
redsolutioncms/media/img/admin/deleted-overlay.gif
redsolutioncms/media/img/admin/icon-no.gif
redsolutioncms/media/img/admin/icon-unknown.gif
redsolutioncms/media/img/admin/icon-yes.gif
redsolutioncms/media/img/admin/icon_addlink.gif
