Metadata-Version: 1.0
Name: redsolutioncms
Version: 0.0.4
Summary: Redsolution CMS allows to create websites quickly, with wizard interface.
Home-page: http://www.redsoluthioncms.org
Author: Ivan Gromov
Author-email: ivan.gromov@redsolution.ru
License: LGPL
Keywords: django news
Platform: UNKNOWN
Classifier: Development Status :: 3 - Alpha
Classifier: Intended Audience :: Developers
Classifier: License :: OSI Approved :: GNU General Public License (GPL)
Classifier: Framework :: Django
Classifier: Environment :: Web Environment
Classifier: Natural Language :: Russian
Classifier: Natural Language :: English
Classifier: Operating System :: OS Independent
Classifier: Programming Language :: Python
Classifier: Topic :: Internet :: WWW/HTTP :: Dynamic Content :: News/Diary
